{
  "__file": "wp_block",
  "title": "工商财税-知识产权头部banner",
  "content": "<!-- wp:themepark-block/themepark-area {\"bimg\":[{\"uploading\":false,\"date\":1640246874000,\"filename\":\"zhishichanquan.jpg\",\"menuOrder\":0,\"uploadedTo\":16,\"type\":\"image\",\"subtype\":\"jpeg\",\"id\":486,\"title\":\"zhishichanquan\",\"url\":\"http://data.themepark.com.cn/2021/n/smartenterprise_data/qy11/uploads/2021/12/zhishichanquan.jpg\",\"link\":\"http://themetest3.local/%e7%9f%a5%e8%af%86%e4%ba%a7%e6%9d%83/zhishichanquan/\",\"alt\":\"\",\"author\":\"1\",\"description\":\"\",\"caption\":\"\",\"name\":\"zhishichanquan\",\"status\":\"inherit\",\"modified\":1640246874000,\"mime\":\"image/jpeg\",\"icon\":\"http://themetest3.local/wp-includes/images/media/default.png\",\"dateFormatted\":\"2021年12月23日\",\"nonces\":{\"update\":\"b2b1c61db0\",\"delete\":\"06cda49c09\",\"edit\":\"9e994b122c\"},\"editLink\":\"http://themetest3.local/wp-admin/post.php?post=486\\u0026action=edit\",\"meta\":false,\"authorName\":\"admin\",\"authorLink\":\"http://themetest3.local/wp-admin/profile.php\",\"uploadedToTitle\":\"知识产权\",\"uploadedToLink\":\"http://themetest3.local/wp-admin/post.php?post=16\\u0026action=edit\",\"filesizeInBytes\":56815,\"filesizeHumanReadable\":\"55 KB\",\"context\":\"\",\"height\":400,\"width\":1476,\"orientation\":\"landscape\",\"sizes\":{\"thumbnail\":{\"height\":150,\"width\":150,\"url\":\"http://data.themepark.com.cn/2021/n/smartenterprise_data/qy11/uploads/2021/12/zhishichanquan-150x150.jpg\",\"orientation\":\"landscape\"},\"medium\":{\"height\":81,\"width\":300,\"url\":\"http://data.themepark.com.cn/2021/n/smartenterprise_data/qy11/uploads/2021/12/zhishichanquan-300x81.jpg\",\"orientation\":\"landscape\"},\"large\":{\"height\":278,\"width\":1024,\"url\":\"http://data.themepark.com.cn/2021/n/smartenterprise_data/qy11/uploads/2021/12/zhishichanquan-1024x278.jpg\",\"orientation\":\"landscape\"},\"full\":{\"url\":\"http://data.themepark.com.cn/2021/n/smartenterprise_data/qy11/uploads/2021/12/zhishichanquan.jpg\",\"height\":400,\"width\":1476,\"orientation\":\"landscape\"}},\"compat\":{\"item\":\"\",\"meta\":\"\"}}],\"bimg2\":[{\"uploading\":false,\"date\":\"2021-12-23T08:07:54.000Z\",\"filename\":\"zhishichanquan.jpg\",\"menuOrder\":0,\"uploadedTo\":16,\"type\":\"image\",\"subtype\":\"jpeg\",\"id\":486,\"title\":\"zhishichanquan\",\"url\":\"http://data.themepark.com.cn/2021/n/smartenterprise_data/qy11/uploads/2021/12/zhishichanquan.jpg\",\"link\":\"http://themetest3.local/%e7%9f%a5%e8%af%86%e4%ba%a7%e6%9d%83/zhishichanquan/\",\"alt\":\"\",\"author\":\"1\",\"description\":\"\",\"caption\":\"\",\"name\":\"zhishichanquan\",\"status\":\"inherit\",\"modified\":\"2021-12-23T08:07:54.000Z\",\"mime\":\"image/jpeg\",\"icon\":\"http://themetest3.local/wp-includes/images/media/default.png\",\"dateFormatted\":\"2021年12月23日\",\"nonces\":{\"update\":\"b2b1c61db0\",\"delete\":\"06cda49c09\",\"edit\":\"9e994b122c\"},\"editLink\":\"http://themetest3.local/wp-admin/post.php?post=486\\u0026action=edit\",\"meta\":false,\"authorName\":\"admin\",\"authorLink\":\"http://themetest3.local/wp-admin/profile.php\",\"uploadedToTitle\":\"知识产权\",\"uploadedToLink\":\"http://themetest3.local/wp-admin/post.php?post=16\\u0026action=edit\",\"filesizeInBytes\":56815,\"filesizeHumanReadable\":\"55 KB\",\"context\":\"\",\"height\":400,\"width\":1476,\"orientation\":\"landscape\",\"sizes\":{\"thumbnail\":{\"height\":150,\"width\":150,\"url\":\"http://data.themepark.com.cn/2021/n/smartenterprise_data/qy11/uploads/2021/12/zhishichanquan-150x150.jpg\",\"orientation\":\"landscape\"},\"medium\":{\"height\":81,\"width\":300,\"url\":\"http://data.themepark.com.cn/2021/n/smartenterprise_data/qy11/uploads/2021/12/zhishichanquan-300x81.jpg\",\"orientation\":\"landscape\"},\"large\":{\"height\":278,\"width\":1024,\"url\":\"http://data.themepark.com.cn/2021/n/smartenterprise_data/qy11/uploads/2021/12/zhishichanquan-1024x278.jpg\",\"orientation\":\"landscape\"},\"full\":{\"url\":\"http://data.themepark.com.cn/2021/n/smartenterprise_data/qy11/uploads/2021/12/zhishichanquan.jpg\",\"height\":400,\"width\":1476,\"orientation\":\"landscape\"}},\"compat\":{\"item\":\"\",\"meta\":\"\"}}],\"bimgp1\":true,\"bimgp2\":true,\"bimgp4\":\"center\",\"top\":125,\"className\":\"bom30 top30\"} -->\n<section class=\"wp-block-themepark-block-themepark-area block_layout thempark-block undefined bom30 top30\" id=\"\" style=\"padding-top:125px;\"><div class=\"block_layout_in\"><!-- wp:column {\"className\":\"block_layout_in\"} -->\n<div class=\"wp-block-column block_layout_in\"><!-- wp:heading {\"textAlign\":\"center\",\"level\":1,\"textColor\":\"white\",\"fontSize\":\"large\"} -->\n<h1 class=\"has-text-align-center has-white-color has-text-color has-large-font-size\">商标注册 / 版权登记</h1>\n<!-- /wp:heading -->\n\n<!-- wp:paragraph {\"align\":\"center\",\"textColor\":\"white\",\"fontSize\":\"medium\"} -->\n<p class=\"has-text-align-center has-white-color has-text-color has-medium-font-size\">Trademark registration / copyright registration</p>\n<!-- /wp:paragraph -->\n\n<!-- wp:paragraph -->\n<p></p>\n<!-- /wp:paragraph -->\n\n<!-- wp:paragraph {\"align\":\"center\",\"textColor\":\"white\",\"fontSize\":\"medium\"} -->\n<p class=\"has-text-align-center has-white-color has-text-color has-medium-font-size\">易办理 | 快申报 | 高通过</p>\n<!-- /wp:paragraph --></div>\n<!-- /wp:column --></div><div class=\"layout_badh\"><div class=\"PcOnly themepark-block_layout_ba lazyload \" style=\"background-repeat:no-repeat;background-size:cover;background-position:center;\" data-src=\"http://data.themepark.com.cn/2021/n/smartenterprise_data/qy11/uploads/2021/12/zhishichanquan.jpg\"></div></div></section>\n<!-- /wp:themepark-block/themepark-area -->"
}